{"title":"Squareup","version":"v1","baseUri":"https://connect.squareup.com/{version}","baseUriParameters":{"version":{"name":"version","displayName":"version","type":"string","required":true,"repeat":false,"enum":["v1"],"__METADATA__":{"calculated":true,"primitiveValuesMeta":{"displayName":{"calculated":true},"type":{"insertedAsDefault":true},"required":{"insertedAsDefault":true},"repeat":{"insertedAsDefault":true},"enum":{"calculated":true}}}}},"protocols":["HTTPS"],"mediaType":"application/json","schemas":[{"error":"Can not resolve schemas/error-schema.json"},{"payments":"Can not resolve schemas/payments-schema.json"},{"payment":"Can not resolve schemas/payment-schema.json"},{"settlements":"Can not resolve schemas/settlements-schema.json"},{"settlement":"Can not resolve schemas/settlement-schema.json"},{"refundReq":"Can not resolve schemas/refundReq-schema.json"},{"refund":"Can not resolve schemas/refund-schema.json"},{"refunds":"Can not resolve schemas/refunds-schema.json"},{"merchant":"Can not resolve schemas/merchant-schema.json"},{"bankAccounts":"Can not resolve schemas/bankAccounts-schema.json"},{"bankAccount":"Can not resolve schemas/bankAccount-schema.json"},{"itemReq":"Can not resolve schemas/itemReq-schema.json"},{"items":"Can not resolve schemas/items-schema.json"},{"createImage":"Can not resolve schemas/createImage-schema.json"},{"feeReq":"Can not resolve schemas/feeReq-schema.json"},{"fee":"Can not resolve schemas/fee-schema.json"},{"fees":"Can not resolve schemas/fees-schema.json"},{"success":"Can not resolve schemas/success-schema.json"},{"pageReq":"Can not resolve schemas/pageReq-schema.json"},{"page":"Can not resolve schemas/page-schema.json"},{"pages":"Can not resolve schemas/pages-schema.json"},{"pageCellReq":"Can not resolve schemas/pageCellReq-schema.json"},{"pageCell":"Can not resolve schemas/pageCell-schema.json"},{"batchRequest":"Can not resolve schemas/batchRequest-schema.json"},{"batchResponse":"Can not resolve schemas/batchResponse-schema.json"},{"merchantBusiness":"Can not resolve schemas/merchantBusiness-schema.json"},{"locations":"Can not resolve schemas/locations-schema.json"},{"item":"Can not resolve schemas/item-schema.json"},{"itemVariationReq":"Can not resolve schemas/itemVariationReq-schema.json"},{"itemVariation":"Can not resolve schemas/itemVariation-schema.json"},{"inventoryEntrys":"Can not resolve schemas/inventoryEntrys-schema.json"},{"inventoryEntryReq":"Can not resolve schemas/inventoryEntryReq-schema.json"},{"inventoryEntry":"Can not resolve schemas/inventoryEntry-schema.json"},{"modifierListReq":"Can not resolve schemas/modifierListReq-schema.json"},{"modifierList":"Can not resolve schemas/modifierList-schema.json"},{"modifierLists":"Can not resolve schemas/modifierLists-schema.json"},{"modifierOptionReq":"Can not resolve schemas/modifierOptionReq-schema.json"},{"modifierOption":"Can not resolve schemas/modifierOption-schema.json"},{"categoryReq":"Can not resolve schemas/categoryReq-schema.json"},{"category":"Can not resolve schemas/category-schema.json"},{"categories":"Can not resolve schemas/categories-schema.json"},{"discountReq":"Can not resolve schemas/discountReq-schema.json"},{"discount":"Can not resolve schemas/discount-schema.json"},{"discounts":"Can not resolve schemas/discounts-schema.json"}],"traits":[{"successable":{"securedBy":["oauth_2_0"],"name":"successable","__METADATA__":{"primitiveValuesMeta":{"securedBy":{"calculated":true}}}}},{"listable":{"securedBy":["oauth_2_0"],"name":"listable","__METADATA__":{"primitiveValuesMeta":{"securedBy":{"calculated":true}}}}},{"dateRangeable":{"securedBy":["oauth_2_0"],"name":"dateRangeable","__METADATA__":{"primitiveValuesMeta":{"securedBy":{"calculated":true}}}}},{"responseable":{"securedBy":["oauth_2_0"],"name":"responseable","__METADATA__":{"primitiveValuesMeta":{"securedBy":{"calculated":true}}}}},{"paginatable":{"securedBy":["oauth_2_0"],"name":"paginatable","__METADATA__":{"primitiveValuesMeta":{"securedBy":{"calculated":true}}}}}],"securedBy":["oauth_2_0"],"securitySchemes":[{"oauth_2_0":{"name":"oauth_2_0"}}],"resourceTypes":[{"basic":{"name":"basic","securedBy":["oauth_2_0"],"__METADATA__":{"primitiveValuesMeta":{"securedBy":{"calculated":true}}}}}],"resources":[{"relativeUri":"/{merchant_id}","securedBy":["oauth_2_0"],"uriParameters":{"merchant_id":{"name":"merchant_id","displayName":"merchant_id","type":"string","required":true,"repeat":false,"description":"If you haven't, specify 'me' for the Connect API to automatically determine your merchant ID based on your request's access token.","__METADATA__":{"primitiveValuesMeta":{"type":{"insertedAsDefault":true},"repeat":{"insertedAsDefault":true}}}}},"methods":[{"responses":{"200":{"code":"200","body":{"application/json":{"name":"application/json","schema":"merchant","example":"Can not resolve examples/merchant-example.json","schemaContent":"Can not resolve schemas/merchant-schema.json"}}}},"protocols":["HTTPS"],"securedBy":["oauth_2_0"],"description":"Provides a merchant's account information, such as business name and email address.","method":"get","__METADATA__":{"primitiveValuesMeta":{"protocols":{"calculated":true},"securedBy":{"calculated":true}}}}],"resources":[{"relativeUri":"/payments","type":"basic","securedBy":["oauth_2_0"],"methods":[{"responses":{"200":{"code":"200","body":{"application/json":{"name":"application/json","schema":"payments","example":"Can not resolve examples/payments-example.json","schemaContent":"Can not resolve schemas/payments-schema.json"}}}},"protocols":["HTTPS"],"securedBy":["oauth_2_0"],"description":"Provides summary information for all payments taken by a merchant or any of the merchant's mobile staff during a date range.","method":"get","is":["dateRangeable","listable","paginatable"],"__METADATA__":{"primitiveValuesMeta":{"protocols":{"calculated":true},"securedBy":{"calculated":true}}}}],"resources":[{"relativeUri":"/{payment_id}","securedBy":["oauth_2_0"],"uriParameters":{"payment_id":{"name":"payment_id","displayName":"payment_id","type":"string","required":true,"repeat":false,"__METADATA__":{"calculated":true,"primitiveValuesMeta":{"displayName":{"calculated":true},"type":{"insertedAsDefault":true},"required":{"insertedAsDefault":true},"repeat":{"insertedAsDefault":true}}}}},"methods":[{"responses":{"200":{"code":"200","body":{"application/json":{"name":"application/json","schema":"payment","example":"Can not resolve examples/payment-example.json","schemaContent":"Can not resolve schemas/payment-schema.json"}}}},"protocols":["HTTPS"],"securedBy":["oauth_2_0"],"description":"Provides comprehensive information for a single payment.","method":"get","__METADATA__":{"primitiveValuesMeta":{"protocols":{"calculated":true},"securedBy":{"calculated":true}}}}],"displayName":"/{payment_id}","__METADATA__":{"primitiveValuesMeta":{"securedBy":{"calculated":true},"displayName":{"calculated":true}}},"relativeUriPathSegments":["{payment_id}"],"absoluteUri":"https://connect.squareup.com/{version}/{merchant_id}/payments/{payment_id}"}],"displayName":"/payments","__METADATA__":{"primitiveValuesMeta":{"securedBy":{"calculated":true},"displayName":{"calculated":true}}},"relativeUriPathSegments":["payments"],"absoluteUri":"https://connect.squareup.com/{version}/{merchant_id}/payments"},{"relativeUri":"/settlements","securedBy":["oauth_2_0"],"methods":[{"responses":{"200":{"code":"200","body":{"application/json":{"name":"application/json","schema":"settlements","example":"Can not resolve examples/settlements-example.json","schemaContent":"Can not resolve schemas/settlements-schema.json"}}}},"protocols":["HTTPS"],"securedBy":["oauth_2_0"],"queryParameters":{"status":{"name":"status","displayName":"status","type":"string","required":false,"repeat":false,"description":"Provide this parameter to retrieve only settlements with a particular status","enum":["SENT","FAILED"],"__METADATA__":{"primitiveValuesMeta":{"displayName":{"calculated":true},"type":{"insertedAsDefault":true},"required":{"insertedAsDefault":true},"repeat":{"insertedAsDefault":true}}}}},"description":"Provides summary information for all deposits and withdrawals initiated by Square to a merchant's bank account during a date range.","method":"get","is":["dateRangeable","listable","paginatable"],"__METADATA__":{"primitiveValuesMeta":{"protocols":{"calculated":true},"securedBy":{"calculated":true}}}}],"resources":[{"relativeUri":"/{settlement_id}","securedBy":["oauth_2_0"],"uriParameters":{"settlement_id":{"name":"settlement_id","displayName":"settlement_id","type":"string","required":true,"repeat":false,"__METADATA__":{"calculated":true,"primitiveValuesMeta":{"displayName":{"calculated":true},"type":{"insertedAsDefault":true},"required":{"insertedAsDefault":true},"repeat":{"insertedAsDefault":true}}}}},"methods":[{"responses":{"200":{"code":"200","body":{"application/json":{"name":"application/json","schema":"settlement","example":"Can not resolve examples/settlement-example.json","schemaContent":"Can not resolve schemas/settlement-schema.json"}}}},"protocols":["HTTPS"],"securedBy":["oauth_2_0"],"description":"Provides comprehensive information for a single settlement, including the entries that contribute to the settlement's total.","method":"get","__METADATA__":{"primitiveValuesMeta":{"protocols":{"calculated":true},"securedBy":{"calculated":true}}}}],"displayName":"/{settlement_id}","__METADATA__":{"primitiveValuesMeta":{"securedBy":{"calculated":true},"displayName":{"calculated":true}}},"relativeUriPathSegments":["{settlement_id}"],"absoluteUri":"https://connect.squareup.com/{version}/{merchant_id}/settlements/{settlement_id}"}],"displayName":"/settlements","__METADATA__":{"primitiveValuesMeta":{"securedBy":{"calculated":true},"displayName":{"calculated":true}}},"relativeUriPathSegments":["settlements"],"absoluteUri":"https://connect.squareup.com/{version}/{merchant_id}/settlements"},{"relativeUri":"/refunds","securedBy":["oauth_2_0"],"methods":[{"responses":{"200":{"code":"200","body":{"application/json":{"name":"application/json","schema":"refund","example":"Can not resolve examples/refund-example.json","schemaContent":"Can not resolve schemas/refund-schema.json"}}}},"body":{"application/json":{"name":"application/json","schema":"refundReq","example":"Can not resolve examples/refundReq-example.json","schemaContent":"Can not resolve schemas/refundReq-schema.json"}},"protocols":["HTTPS"],"securedBy":["oauth_2_0"],"description":"","method":"post","__METADATA__":{"primitiveValuesMeta":{"protocols":{"calculated":true},"securedBy":{"calculated":true}}}},{"responses":{"200":{"code":"200","body":{"application/json":{"name":"application/json","schema":"refunds","example":"Can not resolve examples/refunds-example.json","schemaContent":"Can not resolve schemas/refunds-schema.json"}}}},"protocols":["HTTPS"],"securedBy":["oauth_2_0"],"method":"get","is":["dateRangeable","listable","paginatable"],"__METADATA__":{"primitiveValuesMeta":{"protocols":{"calculated":true},"securedBy":{"calculated":true}}}},{"responses":{"200":{"code":"200","body":{"application/json":{"name":"application/json","schema":"refunds","example":"Can not resolve examples/refunds-example.json","schemaContent":"Can not resolve schemas/refunds-schema.json"}}}},"protocols":["HTTPS"],"securedBy":["oauth_2_0"],"method":"delete","is":["dateRangeable","listable","paginatable"],"__METADATA__":{"primitiveValuesMeta":{"protocols":{"calculated":true},"securedBy":{"calculated":true}}}}],"displayName":"/refunds","__METADATA__":{"primitiveValuesMeta":{"securedBy":{"calculated":true},"displayName":{"calculated":true}}},"relativeUriPathSegments":["refunds"],"absoluteUri":"https://connect.squareup.com/{version}/{merchant_id}/refunds"},{"relativeUri":"/orders","securedBy":["oauth_2_0"],"methods":[{"responses":{"200":{"code":"200","body":{"application/json":{"name":"application/json"}}}},"protocols":["HTTPS"],"securedBy":["oauth_2_0"],"method":"get","is":["listable","paginatable"],"__METADATA__":{"primitiveValuesMeta":{"protocols":{"calculated":true},"securedBy":{"calculated":true}}}}],"resources":[{"relativeUri":"/{order_id}","securedBy":["oauth_2_0"],"uriParameters":{"order_id":{"name":"order_id","displayName":"order_id","type":"string","required":true,"repeat":false,"__METADATA__":{"calculated":true,"primitiveValuesMeta":{"displayName":{"calculated":true},"type":{"insertedAsDefault":true},"required":{"insertedAsDefault":true},"repeat":{"insertedAsDefault":true}}}}},"methods":[{"responses":{"200":{"code":"200","body":{"application/json":{"name":"application/json"}}}},"protocols":["HTTPS"],"securedBy":["oauth_2_0"],"description":"Provides comprehensive information for a single Square Market order, including the order's history.","method":"get","__METADATA__":{"primitiveValuesMeta":{"protocols":{"calculated":true},"securedBy":{"calculated":true}}}},{"responses":{"200":{"code":"200","body":{"application/json":{"name":"application/json"}}}},"protocols":["HTTPS"],"securedBy":["oauth_2_0"],"description":"Updates the details of a Square Market order.","method":"put","__METADATA__":{"primitiveValuesMeta":{"protocols":{"calculated":true},"securedBy":{"calculated":true}}}}],"displayName":"/{order_id}","__METADATA__":{"primitiveValuesMeta":{"securedBy":{"calculated":true},"displayName":{"calculated":true}}},"relativeUriPathSegments":["{order_id}"],"absoluteUri":"https://connect.squareup.com/{version}/{merchant_id}/orders/{order_id}"}],"displayName":"/orders","__METADATA__":{"primitiveValuesMeta":{"securedBy":{"calculated":true},"displayName":{"calculated":true}}},"relativeUriPathSegments":["orders"],"absoluteUri":"https://connect.squareup.com/{version}/{merchant_id}/orders"},{"relativeUri":"/bank-accounts","securedBy":["oauth_2_0"],"methods":[{"responses":{"200":{"code":"200","body":{"application/json":{"name":"application/json","schema":"bankAccounts","example":"Can not resolve examples/bankAccounts-example.json","schemaContent":"Can not resolve schemas/bankAccounts-schema.json"}}}},"protocols":["HTTPS"],"securedBy":["oauth_2_0"],"description":"Provides non-confidential details for all of a merchant's associated bank accounts.","method":"get","__METADATA__":{"primitiveValuesMeta":{"protocols":{"calculated":true},"securedBy":{"calculated":true}}}}],"resources":[{"relativeUri":"/{bank_account_id}","securedBy":["oauth_2_0"],"uriParameters":{"bank_account_id":{"name":"bank_account_id","displayName":"bank_account_id","type":"string","required":true,"repeat":false,"__METADATA__":{"calculated":true,"primitiveValuesMeta":{"displayName":{"calculated":true},"type":{"insertedAsDefault":true},"required":{"insertedAsDefault":true},"repeat":{"insertedAsDefault":true}}}}},"methods":[{"responses":{"200":{"code":"200","body":{"application/json":{"name":"application/json","schema":"bankAccount","example":"Can not resolve examples/bankAccount-example.json","schemaContent":"Can not resolve schemas/bankAccount-schema.json"}}}},"protocols":["HTTPS"],"securedBy":["oauth_2_0"],"description":"Provides non-confidential details for a merchant's associated bank account.","method":"get","__METADATA__":{"primitiveValuesMeta":{"protocols":{"calculated":true},"securedBy":{"calculated":true}}}}],"displayName":"/{bank_account_id}","__METADATA__":{"primitiveValuesMeta":{"securedBy":{"calculated":true},"displayName":{"calculated":true}}},"relativeUriPathSegments":["{bank_account_id}"],"absoluteUri":"https://connect.squareup.com/{version}/{merchant_id}/bank-accounts/{bank_account_id}"}],"displayName":"/bank-accounts","__METADATA__":{"primitiveValuesMeta":{"securedBy":{"calculated":true},"displayName":{"calculated":true}}},"relativeUriPathSegments":["bank-accounts"],"absoluteUri":"https://connect.squareup.com/{version}/{merchant_id}/bank-accounts"},{"relativeUri":"/items","securedBy":["oauth_2_0"],"methods":[{"responses":{"200":{"code":"200","body":{"application/json":{"name":"application/json","schema":"item","example":"Can not resolve examples/item-example.json","schemaContent":"Can not resolve schemas/item-schema.json"}}}},"body":{"application/json":{"name":"application/json","schema":"itemReq","example":"Can not resolve examples/itemReq-example.json","schemaContent":"Can not resolve schemas/itemReq-schema.json"}},"protocols":["HTTPS"],"securedBy":["oauth_2_0"],"description":"Creates an item and at least one variation for it.","method":"post","__METADATA__":{"primitiveValuesMeta":{"protocols":{"calculated":true},"securedBy":{"calculated":true}}}},{"responses":{"200":{"code":"200","body":{"application/json":{"name":"application/json","schema":"items","example":"Can not resolve examples/items-example.json","schemaContent":"Can not resolve schemas/items-schema.json"}}}},"protocols":["HTTPS"],"securedBy":["oauth_2_0"],"description":"Provides summary information for all of a merchant's items.","method":"get","__METADATA__":{"primitiveValuesMeta":{"protocols":{"calculated":true},"securedBy":{"calculated":true}}}}],"resources":[{"relativeUri":"/{item_id}","securedBy":["oauth_2_0"],"uriParameters":{"item_id":{"name":"item_id","displayName":"item_id","type":"string","required":true,"repeat":false,"__METADATA__":{"calculated":true,"primitiveValuesMeta":{"displayName":{"calculated":true},"type":{"insertedAsDefault":true},"required":{"insertedAsDefault":true},"repeat":{"insertedAsDefault":true}}}}},"methods":[{"responses":{"200":{"code":"200","body":{"application/json":{"name":"application/json","schema":"itemReq","example":"Can not resolve examples/item-example.json","schemaContent":"Can not resolve schemas/itemReq-schema.json"}}}},"protocols":["HTTPS"],"securedBy":["oauth_2_0"],"description":"Provides the details for a single item, including associated modifier lists and fees.","method":"get","__METADATA__":{"primitiveValuesMeta":{"protocols":{"calculated":true},"securedBy":{"calculated":true}}}},{"responses":{"200":{"code":"200","body":{"application/json":{"name":"application/json","schema":"item","example":"Can not resolve examples/item-example.json","schemaContent":"Can not resolve schemas/item-schema.json"}}}},"body":{"application/json":{"name":"application/json","schema":"itemReq","example":"Can not resolve examples/itemReq-example.json","schemaContent":"Can not resolve schemas/itemReq-schema.json"}},"protocols":["HTTPS"],"securedBy":["oauth_2_0"],"description":"Modifies the core details of an existing item.","method":"put","__METADATA__":{"primitiveValuesMeta":{"protocols":{"calculated":true},"securedBy":{"calculated":true}}}},{"protocols":["HTTPS"],"securedBy":["oauth_2_0"],"description":"Deletes an existing item and all item variations associated with it.","method":"delete","is":["successable"],"__METADATA__":{"primitiveValuesMeta":{"protocols":{"calculated":true},"securedBy":{"calculated":true}}}}],"resources":[{"relativeUri":"/image","securedBy":["oauth_2_0"],"methods":[{"responses":{"200":{"code":"200","body":{"application/json":{"name":"application/json","schema":"createImage","example":"Can not resolve examples/createImage-example.json","schemaContent":"Can not resolve schemas/createImage-schema.json"}}}},"body":{"multipart/form-data":{"name":"multipart/form-data","formParameters":{"image_data":{"name":"image_data","displayName":"image_data","type":"string","required":false,"repeat":false,"description":"The image's binary data.","__METADATA__":{"primitiveValuesMeta":{"displayName":{"calculated":true},"type":{"insertedAsDefault":true},"required":{"insertedAsDefault":true},"repeat":{"insertedAsDefault":true}}}}}}},"protocols":["HTTPS"],"securedBy":["oauth_2_0"],"description":"Uploads a JPEG or PNG image and sets it as the master image for an item.","method":"post","__METADATA__":{"primitiveValuesMeta":{"protocols":{"calculated":true},"securedBy":{"calculated":true}}}}],"displayName":"/image","__METADATA__":{"primitiveValuesMeta":{"securedBy":{"calculated":true},"displayName":{"calculated":true}}},"relativeUriPathSegments":["image"],"absoluteUri":"https://connect.squareup.com/{version}/{merchant_id}/items/{item_id}/image"},{"relativeUri":"/variations","securedBy":["oauth_2_0"],"methods":[{"responses":{"200":{"code":"200","body":{"application/json":{"name":"application/json","schema":"itemVariation","example":"Can not resolve examples/itemVariation-example.json","schemaContent":"Can not resolve schemas/itemVariation-schema.json"}}}},"body":{"application/json":{"name":"application/json","schema":"itemVariationReq","example":"Can not resolve examples/itemVariationReq-example.json","schemaContent":"Can not resolve schemas/itemVariationReq-schema.json"}},"protocols":["HTTPS"],"securedBy":["oauth_2_0"],"description":"Creates an item variation for an existing item.","method":"post","__METADATA__":{"primitiveValuesMeta":{"protocols":{"calculated":true},"securedBy":{"calculated":true}}}}],"resources":[{"relativeUri":"/{variation_id}","securedBy":["oauth_2_0"],"uriParameters":{"variation_id":{"name":"variation_id","displayName":"variation_id","type":"string","required":true,"repeat":false,"__METADATA__":{"calculated":true,"primitiveValuesMeta":{"displayName":{"calculated":true},"type":{"insertedAsDefault":true},"required":{"insertedAsDefault":true},"repeat":{"insertedAsDefault":true}}}}},"methods":[{"responses":{"200":{"code":"200","body":{"application/json":{"name":"application/json","schema":"itemVariation","example":"Can not resolve examples/itemVariation-example.json","schemaContent":"Can not resolve schemas/itemVariation-schema.json"}}}},"body":{"application/json":{"name":"application/json","schema":"itemVariationReq","example":"Can not resolve examples/itemVariationReq-example.json","schemaContent":"Can not resolve schemas/itemVariationReq-schema.json"}},"protocols":["HTTPS"],"securedBy":["oauth_2_0"],"description":"Modifies the details of an existing item variation.","method":"put","__METADATA__":{"primitiveValuesMeta":{"protocols":{"calculated":true},"securedBy":{"calculated":true}}}},{"protocols":["HTTPS"],"securedBy":["oauth_2_0"],"method":"delete","is":["successable"],"__METADATA__":{"primitiveValuesMeta":{"protocols":{"calculated":true},"securedBy":{"calculated":true}}}}],"displayName":"/{variation_id}","__METADATA__":{"primitiveValuesMeta":{"securedBy":{"calculated":true},"displayName":{"calculated":true}}},"relativeUriPathSegments":["{variation_id}"],"absoluteUri":"https://connect.squareup.com/{version}/{merchant_id}/items/{item_id}/variations/{variation_id}"}],"displayName":"/variations","__METADATA__":{"primitiveValuesMeta":{"securedBy":{"calculated":true},"displayName":{"calculated":true}}},"relativeUriPathSegments":["variations"],"absoluteUri":"https://connect.squareup.com/{version}/{merchant_id}/items/{item_id}/variations"},{"relativeUri":"/fees/{fee_id}","securedBy":["oauth_2_0"],"uriParameters":{"fee_id":{"name":"fee_id","displayName":"fee_id","type":"string","required":true,"repeat":false,"__METADATA__":{"calculated":true,"primitiveValuesMeta":{"displayName":{"calculated":true},"type":{"insertedAsDefault":true},"required":{"insertedAsDefault":true},"repeat":{"insertedAsDefault":true}}}}},"methods":[{"protocols":["HTTPS"],"securedBy":["oauth_2_0"],"description":"Associates a fee with an item, meaning the fee is automatically applied to the item in Square Register.","method":"put","__METADATA__":{"primitiveValuesMeta":{"protocols":{"calculated":true},"securedBy":{"calculated":true}}}},{"protocols":["HTTPS"],"securedBy":["oauth_2_0"],"description":"Removes a fee assocation from an item, meaning the fee is no longer automatically applied to the item in Square Register.","method":"delete","__METADATA__":{"primitiveValuesMeta":{"protocols":{"calculated":true},"securedBy":{"calculated":true}}}}],"displayName":"/fees/{fee_id}","__METADATA__":{"primitiveValuesMeta":{"securedBy":{"calculated":true},"displayName":{"calculated":true}}},"relativeUriPathSegments":["fees","{fee_id}"],"absoluteUri":"https://connect.squareup.com/{version}/{merchant_id}/items/{item_id}/fees/{fee_id}"},{"relativeUri":"/modifier-lists/{modifier_list_id}","securedBy":["oauth_2_0"],"uriParameters":{"modifier_list_id":{"name":"modifier_list_id","displayName":"modifier_list_id","type":"string","required":true,"repeat":false,"__METADATA__":{"calculated":true,"primitiveValuesMeta":{"displayName":{"calculated":true},"type":{"insertedAsDefault":true},"required":{"insertedAsDefault":true},"repeat":{"insertedAsDefault":true}}}}},"methods":[{"responses":{"200":{"code":"200","body":{"application/json":{"name":"application/json","schema":"item","schemaContent":"Can not resolve schemas/item-schema.json"}}}},"protocols":["HTTPS"],"securedBy":["oauth_2_0"],"description":"Associates a modifier list with an item, meaning modifier options from the list can be applied to the item.","method":"put","__METADATA__":{"primitiveValuesMeta":{"protocols":{"calculated":true},"securedBy":{"calculated":true}}}},{"responses":{"200":{"code":"200","body":{"application/json":{"name":"application/json","schema":"item","schemaContent":"Can not resolve schemas/item-schema.json"}}}},"protocols":["HTTPS"],"securedBy":["oauth_2_0"],"method":"delete","__METADATA__":{"primitiveValuesMeta":{"protocols":{"calculated":true},"securedBy":{"calculated":true}}}}],"displayName":"/modifier-lists/{modifier_list_id}","__METADATA__":{"primitiveValuesMeta":{"securedBy":{"calculated":true},"displayName":{"calculated":true}}},"relativeUriPathSegments":["modifier-lists","{modifier_list_id}"],"absoluteUri":"https://connect.squareup.com/{version}/{merchant_id}/items/{item_id}/modifier-lists/{modifier_list_id}"}],"displayName":"/{item_id}","__METADATA__":{"primitiveValuesMeta":{"securedBy":{"calculated":true},"displayName":{"calculated":true}}},"relativeUriPathSegments":["{item_id}"],"absoluteUri":"https://connect.squareup.com/{version}/{merchant_id}/items/{item_id}"}],"displayName":"/items","__METADATA__":{"primitiveValuesMeta":{"securedBy":{"calculated":true},"displayName":{"calculated":true}}},"relativeUriPathSegments":["items"],"absoluteUri":"https://connect.squareup.com/{version}/{merchant_id}/items"},{"relativeUri":"/inventory","securedBy":["oauth_2_0"],"methods":[{"responses":{"200":{"code":"200","body":{"application/json":{"name":"application/json","schema":"inventoryEntrys","example":"[\n  {\n    \"variation_id\" : \"cb890728-cfdc-4690-9e03-349f964f756r\" ,\n    \"quantity_on_hand\" : 50\n  }\n]","schemaContent":"Can not resolve schemas/inventoryEntrys-schema.json"}}}},"protocols":["HTTPS"],"securedBy":["oauth_2_0"],"description":"Provides inventory information for all of a merchant's inventory-enabled item variations.","method":"get","__METADATA__":{"primitiveValuesMeta":{"protocols":{"calculated":true},"securedBy":{"calculated":true}}}}],"resources":[{"relativeUri":"/{variation_id}","securedBy":["oauth_2_0"],"uriParameters":{"variation_id":{"name":"variation_id","displayName":"variation_id","type":"string","required":true,"repeat":false,"__METADATA__":{"calculated":true,"primitiveValuesMeta":{"displayName":{"calculated":true},"type":{"insertedAsDefault":true},"required":{"insertedAsDefault":true},"repeat":{"insertedAsDefault":true}}}}},"methods":[{"responses":{"200":{"code":"200","body":{"application/json":{"name":"application/json","schema":"inventoryEntry","example":"Can not resolve examples/inventoryEntry-example.json","schemaContent":"Can not resolve schemas/inventoryEntry-schema.json"}}}},"body":{"application/json":{"name":"application/json","schema":"inventoryEntryReq","example":"Can not resolve examples/inventoryEntryReq-example.json","schemaContent":"Can not resolve schemas/inventoryEntryReq-schema.json"}},"protocols":["HTTPS"],"securedBy":["oauth_2_0"],"description":"Adjusts an item variation's current available inventory.","method":"post","__METADATA__":{"primitiveValuesMeta":{"protocols":{"calculated":true},"securedBy":{"calculated":true}}}}],"displayName":"/{variation_id}","__METADATA__":{"primitiveValuesMeta":{"securedBy":{"calculated":true},"displayName":{"calculated":true}}},"relativeUriPathSegments":["{variation_id}"],"absoluteUri":"https://connect.squareup.com/{version}/{merchant_id}/inventory/{variation_id}"}],"displayName":"/inventory","__METADATA__":{"primitiveValuesMeta":{"securedBy":{"calculated":true},"displayName":{"calculated":true}}},"relativeUriPathSegments":["inventory"],"absoluteUri":"https://connect.squareup.com/{version}/{merchant_id}/inventory"},{"relativeUri":"/modifier-lists","securedBy":["oauth_2_0"],"methods":[{"responses":{"200":{"code":"200","body":{"application/json":{"name":"application/json","schema":"modifierList","example":"Can not resolve examples/modifierList-example.json","schemaContent":"Can not resolve schemas/modifierList-schema.json"}}}},"body":{"application/json":{"name":"application/json","schema":"modifierListReq","example":"Can not resolve examples/modifierListReq-example.json","schemaContent":"Can not resolve schemas/modifierListReq-schema.json"}},"protocols":["HTTPS"],"securedBy":["oauth_2_0"],"description":"Creates an item modifier list and at least one modifier option for it.","method":"post","__METADATA__":{"primitiveValuesMeta":{"protocols":{"calculated":true},"securedBy":{"calculated":true}}}},{"responses":{"200":{"code":"200","body":{"application/json":{"name":"application/json","schema":"modifierLists","example":"Can not resolve examples/modifierLists-example.json","schemaContent":"Can not resolve schemas/modifierLists-schema.json"}}}},"protocols":["HTTPS"],"securedBy":["oauth_2_0"],"description":"Lists all of a merchant's modifier lists.","method":"get","__METADATA__":{"primitiveValuesMeta":{"protocols":{"calculated":true},"securedBy":{"calculated":true}}}}],"resources":[{"relativeUri":"/{modifier_list_id}","securedBy":["oauth_2_0"],"uriParameters":{"modifier_list_id":{"name":"modifier_list_id","displayName":"modifier_list_id","type":"string","required":true,"repeat":false,"__METADATA__":{"calculated":true,"primitiveValuesMeta":{"displayName":{"calculated":true},"type":{"insertedAsDefault":true},"required":{"insertedAsDefault":true},"repeat":{"insertedAsDefault":true}}}}},"methods":[{"responses":{"200":{"code":"200","body":{"application/json":{"name":"application/json"}}}},"protocols":["HTTPS"],"securedBy":["oauth_2_0"],"method":"put","__METADATA__":{"primitiveValuesMeta":{"protocols":{"calculated":true},"securedBy":{"calculated":true}}}},{"protocols":["HTTPS"],"securedBy":["oauth_2_0"],"method":"delete","is":["successable"],"__METADATA__":{"primitiveValuesMeta":{"protocols":{"calculated":true},"securedBy":{"calculated":true}}}}],"resources":[{"relativeUri":"/modifier-options","securedBy":["oauth_2_0"],"methods":[{"responses":{"200":{"code":"200","body":{"application/json":{"name":"application/json","schema":"modifierOption","example":"Can not resolve examples/modifierOption-example.json","schemaContent":"Can not resolve schemas/modifierOption-schema.json"}}}},"body":{"application/json":{"name":"application/json","schema":"modifierOptionReq","example":"Can not resolve examples/modifierOptionReq-example.json","schemaContent":"Can not resolve schemas/modifierOptionReq-schema.json"}},"protocols":["HTTPS"],"securedBy":["oauth_2_0"],"description":"Creates an item modifier option and adds it to a modifier list.","method":"post","__METADATA__":{"primitiveValuesMeta":{"protocols":{"calculated":true},"securedBy":{"calculated":true}}}}],"resources":[{"relativeUri":"/{modifier_option_id}","securedBy":["oauth_2_0"],"uriParameters":{"modifier_option_id":{"name":"modifier_option_id","displayName":"modifier_option_id","type":"string","required":true,"repeat":false,"__METADATA__":{"calculated":true,"primitiveValuesMeta":{"displayName":{"calculated":true},"type":{"insertedAsDefault":true},"required":{"insertedAsDefault":true},"repeat":{"insertedAsDefault":true}}}}},"methods":[{"responses":{"200":{"code":"200","body":{"application/json":{"name":"application/json","schema":"modifierOption","example":"Can not resolve examples/modifierOption-example.json","schemaContent":"Can not resolve schemas/modifierOption-schema.json"}}}},"body":{"application/json":{"name":"application/json","schema":"modifierOptionReq","example":"Can not resolve examples/modifierOptionReq-example.json","schemaContent":"Can not resolve schemas/modifierOptionReq-schema.json"}},"protocols":["HTTPS"],"securedBy":["oauth_2_0"],"description":"Modifies the details of an existing item modifier option.","method":"put","__METADATA__":{"primitiveValuesMeta":{"protocols":{"calculated":true},"securedBy":{"calculated":true}}}},{"protocols":["HTTPS"],"securedBy":["oauth_2_0"],"description":"Deletes an existing item modifier option from a modifier list.","method":"delete","is":["successable"],"__METADATA__":{"primitiveValuesMeta":{"protocols":{"calculated":true},"securedBy":{"calculated":true}}}}],"displayName":"/{modifier_option_id}","__METADATA__":{"primitiveValuesMeta":{"securedBy":{"calculated":true},"displayName":{"calculated":true}}},"relativeUriPathSegments":["{modifier_option_id}"],"absoluteUri":"https://connect.squareup.com/{version}/{merchant_id}/modifier-lists/{modifier_list_id}/modifier-options/{modifier_option_id}"}],"displayName":"/modifier-options","__METADATA__":{"primitiveValuesMeta":{"securedBy":{"calculated":true},"displayName":{"calculated":true}}},"relativeUriPathSegments":["modifier-options"],"absoluteUri":"https://connect.squareup.com/{version}/{merchant_id}/modifier-lists/{modifier_list_id}/modifier-options"}],"displayName":"/{modifier_list_id}","__METADATA__":{"primitiveValuesMeta":{"securedBy":{"calculated":true},"displayName":{"calculated":true}}},"relativeUriPathSegments":["{modifier_list_id}"],"absoluteUri":"https://connect.squareup.com/{version}/{merchant_id}/modifier-lists/{modifier_list_id}"}],"displayName":"/modifier-lists","__METADATA__":{"primitiveValuesMeta":{"securedBy":{"calculated":true},"displayName":{"calculated":true}}},"relativeUriPathSegments":["modifier-lists"],"absoluteUri":"https://connect.squareup.com/{version}/{merchant_id}/modifier-lists"},{"relativeUri":"/categories","securedBy":["oauth_2_0"],"methods":[{"responses":{"200":{"code":"200","body":{"application/json":{"name":"application/json","schema":"category","example":"Can not resolve examples/category-example.json","schemaContent":"Can not resolve schemas/category-schema.json"}}}},"body":{"application/json":{"name":"application/json","schema":"categoryReq","example":"Can not resolve examples/categoryReq-example.json","schemaContent":"Can not resolve schemas/categoryReq-schema.json"}},"protocols":["HTTPS"],"securedBy":["oauth_2_0"],"description":"Creates an item category.","method":"post","__METADATA__":{"primitiveValuesMeta":{"protocols":{"calculated":true},"securedBy":{"calculated":true}}}},{"responses":{"200":{"code":"200","body":{"application/json":{"name":"application/json","schema":"categories","example":"Can not resolve examples/categories-example.json","schemaContent":"Can not resolve schemas/categories-schema.json"}}}},"protocols":["HTTPS"],"securedBy":["oauth_2_0"],"method":"get","__METADATA__":{"primitiveValuesMeta":{"protocols":{"calculated":true},"securedBy":{"calculated":true}}}}],"resources":[{"relativeUri":"/{category_id}","securedBy":["oauth_2_0"],"uriParameters":{"category_id":{"name":"category_id","displayName":"category_id","type":"string","required":true,"repeat":false,"__METADATA__":{"calculated":true,"primitiveValuesMeta":{"displayName":{"calculated":true},"type":{"insertedAsDefault":true},"required":{"insertedAsDefault":true},"repeat":{"insertedAsDefault":true}}}}},"methods":[{"responses":{"200":{"code":"200","body":{"application/json":{"name":"application/json","schema":"category","example":"Can not resolve examples/category-example.json","schemaContent":"Can not resolve schemas/category-schema.json"}}}},"body":{"application/json":{"name":"application/json","schema":"categoryReq","example":"Can not resolve examples/categoryReq-example.json","schemaContent":"Can not resolve schemas/categoryReq-schema.json"}},"protocols":["HTTPS"],"securedBy":["oauth_2_0"],"method":"put","__METADATA__":{"primitiveValuesMeta":{"protocols":{"calculated":true},"securedBy":{"calculated":true}}}},{"protocols":["HTTPS"],"securedBy":["oauth_2_0"],"method":"delete","is":["successable"],"__METADATA__":{"primitiveValuesMeta":{"protocols":{"calculated":true},"securedBy":{"calculated":true}}}}],"displayName":"/{category_id}","__METADATA__":{"primitiveValuesMeta":{"securedBy":{"calculated":true},"displayName":{"calculated":true}}},"relativeUriPathSegments":["{category_id}"],"absoluteUri":"https://connect.squareup.com/{version}/{merchant_id}/categories/{category_id}"}],"displayName":"/categories","__METADATA__":{"primitiveValuesMeta":{"securedBy":{"calculated":true},"displayName":{"calculated":true}}},"relativeUriPathSegments":["categories"],"absoluteUri":"https://connect.squareup.com/{version}/{merchant_id}/categories"},{"relativeUri":"/discounts","securedBy":["oauth_2_0"],"methods":[{"responses":{"200":{"code":"200","body":{"application/json":{"name":"application/json","schema":"discounts","example":"Can not resolve examples/discounts-example.json","schemaContent":"Can not resolve schemas/discounts-schema.json"}}}},"protocols":["HTTPS"],"securedBy":["oauth_2_0"],"description":"Lists all of a merchant's discounts.","method":"get","__METADATA__":{"primitiveValuesMeta":{"protocols":{"calculated":true},"securedBy":{"calculated":true}}}},{"responses":{"200":{"code":"200","body":{"application/json":{"name":"application/json","schema":"discount","example":"Can not resolve examples/discount-example.json","schemaContent":"Can not resolve schemas/discount-schema.json"}}}},"body":{"application/json":{"name":"application/json","schema":"discountReq","example":"Can not resolve examples/discountReq-example.json","schemaContent":"Can not resolve schemas/discountReq-schema.json"}},"protocols":["HTTPS"],"securedBy":["oauth_2_0"],"description":"Creates a discount.","method":"post","__METADATA__":{"primitiveValuesMeta":{"protocols":{"calculated":true},"securedBy":{"calculated":true}}}}],"resources":[{"relativeUri":"/{discount_id}","securedBy":["oauth_2_0"],"uriParameters":{"discount_id":{"name":"discount_id","displayName":"discount_id","type":"string","required":true,"repeat":false,"__METADATA__":{"calculated":true,"primitiveValuesMeta":{"displayName":{"calculated":true},"type":{"insertedAsDefault":true},"required":{"insertedAsDefault":true},"repeat":{"insertedAsDefault":true}}}}},"methods":[{"responses":{"200":{"code":"200","body":{"application/json":{"name":"application/json","schema":"discount","example":"Can not resolve examples/discount-example.json","schemaContent":"Can not resolve schemas/discount-schema.json"}}}},"body":{"application/json":{"name":"application/json","schema":"discountReq","example":"Can not resolve examples/discountReq-example.json","schemaContent":"Can not resolve schemas/discountReq-schema.json"}},"protocols":["HTTPS"],"securedBy":["oauth_2_0"],"description":"Modifies the details of an existing discount.","method":"put","__METADATA__":{"primitiveValuesMeta":{"protocols":{"calculated":true},"securedBy":{"calculated":true}}}},{"protocols":["HTTPS"],"securedBy":["oauth_2_0"],"method":"delete","is":["successable"],"__METADATA__":{"primitiveValuesMeta":{"protocols":{"calculated":true},"securedBy":{"calculated":true}}}}],"displayName":"/{discount_id}","__METADATA__":{"primitiveValuesMeta":{"securedBy":{"calculated":true},"displayName":{"calculated":true}}},"relativeUriPathSegments":["{discount_id}"],"absoluteUri":"https://connect.squareup.com/{version}/{merchant_id}/discounts/{discount_id}"}],"displayName":"/discounts","__METADATA__":{"primitiveValuesMeta":{"securedBy":{"calculated":true},"displayName":{"calculated":true}}},"relativeUriPathSegments":["discounts"],"absoluteUri":"https://connect.squareup.com/{version}/{merchant_id}/discounts"},{"relativeUri":"/fees","securedBy":["oauth_2_0"],"methods":[{"responses":{"200":{"code":"200","body":{"application/json":{"name":"application/json","schema":"fee","example":"Can not resolve examples/fee-example.json","schemaContent":"Can not resolve schemas/fee-schema.json"}}}},"body":{"application/json":{"name":"application/json","schema":"feeReq","example":"Can not resolve examples/feeReq-example.json","schemaContent":"Can not resolve schemas/feeReq-schema.json"}},"protocols":["HTTPS"],"securedBy":["oauth_2_0"],"description":"Creates a fee (tax).","method":"post","__METADATA__":{"primitiveValuesMeta":{"protocols":{"calculated":true},"securedBy":{"calculated":true}}}},{"responses":{"200":{"code":"200","body":{"application/json":{"name":"application/json","schema":"fees","example":"Can not resolve examples/fees-example.json","schemaContent":"Can not resolve schemas/fees-schema.json"}}}},"protocols":["HTTPS"],"securedBy":["oauth_2_0"],"description":"Lists all of a merchant's fees (taxes).","method":"get","is":["paginatable"],"__METADATA__":{"primitiveValuesMeta":{"protocols":{"calculated":true},"securedBy":{"calculated":true}}}}],"resources":[{"relativeUri":"/{fee_id}","securedBy":["oauth_2_0"],"uriParameters":{"fee_id":{"name":"fee_id","displayName":"fee_id","type":"string","required":true,"repeat":false,"__METADATA__":{"calculated":true,"primitiveValuesMeta":{"displayName":{"calculated":true},"type":{"insertedAsDefault":true},"required":{"insertedAsDefault":true},"repeat":{"insertedAsDefault":true}}}}},"methods":[{"responses":{"200":{"code":"200","body":{"application/json":{"name":"application/json","schema":"fee","example":"Can not resolve examples/fee-example.json","schemaContent":"Can not resolve schemas/fee-schema.json"}}}},"body":{"application/json":{"name":"application/json","schema":"feeReq","example":"Can not resolve examples/feeReq-example.json","schemaContent":"Can not resolve schemas/feeReq-schema.json"}},"protocols":["HTTPS"],"securedBy":["oauth_2_0"],"description":"Modifies the details of an existing fee (tax).","method":"put","__METADATA__":{"primitiveValuesMeta":{"protocols":{"calculated":true},"securedBy":{"calculated":true}}}},{"protocols":["HTTPS"],"securedBy":["oauth_2_0"],"method":"delete","is":["successable"],"__METADATA__":{"primitiveValuesMeta":{"protocols":{"calculated":true},"securedBy":{"calculated":true}}}}],"displayName":"/{fee_id}","__METADATA__":{"primitiveValuesMeta":{"securedBy":{"calculated":true},"displayName":{"calculated":true}}},"relativeUriPathSegments":["{fee_id}"],"absoluteUri":"https://connect.squareup.com/{version}/{merchant_id}/fees/{fee_id}"}],"displayName":"/fees","__METADATA__":{"primitiveValuesMeta":{"securedBy":{"calculated":true},"displayName":{"calculated":true}}},"relativeUriPathSegments":["fees"],"absoluteUri":"https://connect.squareup.com/{version}/{merchant_id}/fees"},{"relativeUri":"/pages","securedBy":["oauth_2_0"],"methods":[{"responses":{"200":{"code":"200","body":{"application/json":{"name":"application/json","schema":"page","example":"Can not resolve examples/page-example.json","schemaContent":"Can not resolve schemas/page-schema.json"}}}},"body":{"application/json":{"name":"application/json","schema":"pageReq","example":"Can not resolve examples/pageReq-example.json","schemaContent":"Can not resolve schemas/pageReq-schema.json"}},"protocols":["HTTPS"],"securedBy":["oauth_2_0"],"description":"Creates a Favorites page in Square Register.","method":"post","__METADATA__":{"primitiveValuesMeta":{"protocols":{"calculated":true},"securedBy":{"calculated":true}}}},{"responses":{"200":{"code":"200","body":{"application/json":{"name":"application/json","schema":"pages","example":"Can not resolve examples/pages-example.json","schemaContent":"Can not resolve schemas/pages-schema.json"}}}},"protocols":["HTTPS"],"securedBy":["oauth_2_0"],"method":"get","__METADATA__":{"primitiveValuesMeta":{"protocols":{"calculated":true},"securedBy":{"calculated":true}}}}],"resources":[{"relativeUri":"/{page_id}","securedBy":["oauth_2_0"],"uriParameters":{"page_id":{"name":"page_id","displayName":"page_id","type":"string","required":true,"repeat":false,"__METADATA__":{"calculated":true,"primitiveValuesMeta":{"displayName":{"calculated":true},"type":{"insertedAsDefault":true},"required":{"insertedAsDefault":true},"repeat":{"insertedAsDefault":true}}}}},"methods":[{"responses":{"200":{"code":"200","body":{"application/json":{"name":"application/json","schema":"page","example":"Can not resolve examples/page-example.json","schemaContent":"Can not resolve schemas/page-schema.json"}}}},"body":{"application/json":{"name":"application/json","schema":"pageReq","example":"Can not resolve examples/pageReq-example.json","schemaContent":"Can not resolve schemas/pageReq-schema.json"}},"protocols":["HTTPS"],"securedBy":["oauth_2_0"],"description":"Modifies the details of a Favorites page in Square Register.","method":"put","__METADATA__":{"primitiveValuesMeta":{"protocols":{"calculated":true},"securedBy":{"calculated":true}}}},{"protocols":["HTTPS"],"securedBy":["oauth_2_0"],"method":"delete","is":["successable"],"__METADATA__":{"primitiveValuesMeta":{"protocols":{"calculated":true},"securedBy":{"calculated":true}}}}],"resources":[{"relativeUri":"/cells","securedBy":["oauth_2_0"],"methods":[{"responses":{"200":{"code":"200","body":{"application/json":{"name":"application/json","schema":"pageCell","example":"Can not resolve examples/pageCell-example.json","schemaContent":"Can not resolve schemas/pageCell-schema.json"}}}},"body":{"application/json":{"name":"application/json","schema":"pageCellReq","example":"Can not resolve examples/pageCellReq-example.json","schemaContent":"Can not resolve schemas/pageCellReq-schema.json"}},"protocols":["HTTPS"],"securedBy":["oauth_2_0"],"description":"Modifies a cell of a Favorites page in Square Register.","method":"put","__METADATA__":{"primitiveValuesMeta":{"protocols":{"calculated":true},"securedBy":{"calculated":true}}}},{"protocols":["HTTPS"],"securedBy":["oauth_2_0"],"description":"Deletes a cell from a Favorites page in Square Register.","method":"delete","is":["successable"],"__METADATA__":{"primitiveValuesMeta":{"protocols":{"calculated":true},"securedBy":{"calculated":true}}}}],"displayName":"/cells","__METADATA__":{"primitiveValuesMeta":{"securedBy":{"calculated":true},"displayName":{"calculated":true}}},"relativeUriPathSegments":["cells"],"absoluteUri":"https://connect.squareup.com/{version}/{merchant_id}/pages/{page_id}/cells"}],"displayName":"/{page_id}","__METADATA__":{"primitiveValuesMeta":{"securedBy":{"calculated":true},"displayName":{"calculated":true}}},"relativeUriPathSegments":["{page_id}"],"absoluteUri":"https://connect.squareup.com/{version}/{merchant_id}/pages/{page_id}"}],"displayName":"/pages","__METADATA__":{"primitiveValuesMeta":{"securedBy":{"calculated":true},"displayName":{"calculated":true}}},"relativeUriPathSegments":["pages"],"absoluteUri":"https://connect.squareup.com/{version}/{merchant_id}/pages"},{"relativeUri":"/business","securedBy":["oauth_2_0"],"methods":[{"responses":{"200":{"code":"200","body":{"application/json":{"name":"application/json","schema":"merchantBusiness","example":"Can not resolve examples/merchantBusiness-example.json","schemaContent":"Can not resolve schemas/merchantBusiness-schema.json"}}}},"protocols":["HTTPS"],"securedBy":["oauth_2_0"],"method":"get","__METADATA__":{"primitiveValuesMeta":{"protocols":{"calculated":true},"securedBy":{"calculated":true}}}}],"displayName":"/business","__METADATA__":{"primitiveValuesMeta":{"securedBy":{"calculated":true},"displayName":{"calculated":true}}},"relativeUriPathSegments":["business"],"absoluteUri":"https://connect.squareup.com/{version}/{merchant_id}/business"},{"relativeUri":"/locations","securedBy":["oauth_2_0"],"methods":[{"responses":{"200":{"code":"200","body":{"application/json":{"name":"application/json","schema":"locations","example":"Can not resolve examples/locations-example.json","schemaContent":"Can not resolve schemas/locations-schema.json"}}}},"protocols":["HTTPS"],"securedBy":["oauth_2_0"],"description":"Retrieve an array of Merchant objects containing profile information for the business's locations.","method":"get","__METADATA__":{"primitiveValuesMeta":{"protocols":{"calculated":true},"securedBy":{"calculated":true}}}}],"displayName":"/locations","__METADATA__":{"primitiveValuesMeta":{"securedBy":{"calculated":true},"displayName":{"calculated":true}}},"relativeUriPathSegments":["locations"],"absoluteUri":"https://connect.squareup.com/{version}/{merchant_id}/locations"}],"displayName":"/{merchant_id}","__METADATA__":{"primitiveValuesMeta":{"securedBy":{"calculated":true},"displayName":{"calculated":true}}},"relativeUriPathSegments":["{merchant_id}"],"absoluteUri":"https://connect.squareup.com/{version}/{merchant_id}"},{"relativeUri":"/batch","securedBy":["oauth_2_0"],"methods":[{"responses":{"200":{"code":"200","body":{"application/json":{"name":"application/json","schema":"batchResponse","example":"Can not resolve examples/batchResponse-example.json","schemaContent":"Can not resolve schemas/batchResponse-schema.json"}}}},"body":{"application/json":{"name":"application/json","schema":"batchRequest","example":"Can not resolve examples/batchRequest-example.json","schemaContent":"Can not resolve schemas/batchRequest-schema.json"}},"protocols":["HTTPS"],"securedBy":["oauth_2_0"],"description":"This endpoint's response is an array that contains the response for each batched request.","method":"post","__METADATA__":{"primitiveValuesMeta":{"protocols":{"calculated":true},"securedBy":{"calculated":true}}}}],"displayName":"/batch","__METADATA__":{"primitiveValuesMeta":{"securedBy":{"calculated":true},"displayName":{"calculated":true}}},"relativeUriPathSegments":["batch"],"absoluteUri":"https://connect.squareup.com/{version}/batch"}],"documentation":[{"title":"Headline","content":"Can not resolve docs/headline.md"}],"__METADATA__":{"primitiveValuesMeta":{"protocols":{"calculated":true}}}}